pyHS100/__init__.py
pyHS100/cli.py
pyHS100/discover.py
pyHS100/protocol.py
pyHS100/smartbulb.py
pyHS100/smartdevice.py
pyHS100/smartplug.py
pyHS100/smartstrip.py
pyHS100-0.3.5.2.dist-info/AUTHORS
pyHS100-0.3.5.2.dist-info/LICENSE
pyHS100-0.3.5.2.dist-info/METADATA
pyHS100-0.3.5.2.dist-info/WHEEL
pyHS100-0.3.5.2.dist-info/entry_points.txt
pyHS100-0.3.5.2.dist-info/top_level.txt
pyHS100-0.3.5.2.dist-info/RECORD
