Metadata-Version: 1.2
Name: pyHS100
Version: 0.3.5.2
Summary: Interface for TPLink HS1xx plugs, HS2xx wall switches & LB1xx bulbs
Home-page: https://github.com/GadgetReactor/pyHS100
Author: Sean Seah (GadgetReactor)
Author-email: sean@gadgetreactor.com
License: GPLv3
Platform: UNKNOWN
Requires-Python: >=3.4
